shppy/__init__.py
shppy/run_test.py
shppy-0.0.1.dist-info/METADATA
shppy-0.0.1.dist-info/WHEEL
shppy-0.0.1.dist-info/entry_points.txt
shppy-0.0.1.dist-info/top_level.txt
shppy-0.0.1.dist-info/RECORD
