Metadata-Version: 2.1
Name: shppy
Version: 0.0.1
Summary: Season's High Performance library for Python
Home-page: https://github.com/supercgor/shppy
Author: Chon-Hei Lo
Author-email: siumabon123@gmail.com
Maintainer: Chon-Hei Lo
Maintainer-email: siumabon123@gmail.com
License: MIT License
Classifier: Operating System :: OS Independent
Classifier: License :: OSI Approved :: MIT License
Classifier: Programming Language :: Python :: 3
Requires-Python: >=3.9
Requires-Dist: wheel
Requires-Dist: numpy
Requires-Dist: numba
Requires-Dist: scipy
Requires-Dist: pandas
Requires-Dist: ase
Requires-Dist: matplotlib
